django_view_utils/__about__.py
django_view_utils/__init__.py
django_view_utils/apps.py
django_view_utils/conf.py
django_view_utils/decorators.py
django_view_utils/urls.py
django_view_utils/utils.py
django_view_utils-0.0.4.dist-info/METADATA
django_view_utils-0.0.4.dist-info/WHEEL
django_view_utils-0.0.4.dist-info/licenses/LICENSE.txt
django_view_utils-0.0.4.dist-info/RECORD
